openseespy/__init__.py
openseespy/opensees/__init__.py
openseespy/opensees/opensees.so
openseespy/opensees/OpenSeesPy.dylib
openseespy/.dylibs/libopen-pal.80.dylib
openseespy/.dylibs/libhwloc.15.dylib
openseespy/.dylibs/libevent_pthreads-2.1.7.dylib
openseespy/.dylibs/libaec.0.1.4.dylib
openseespy/.dylibs/libpmix.2.dylib
openseespy/.dylibs/libgfortran.5.dylib
openseespy/.dylibs/libsz.2.0.1.dylib
openseespy/.dylibs/libmpi.40.dylib
openseespy/.dylibs/libquadmath.0.dylib
openseespy/.dylibs/libgcc_s.1.1.dylib
openseespy/.dylibs/libevent_core-2.1.7.dylib
openseespy_mac_arm-3.7.1.4.dist-info/RECORD
openseespy_mac_arm-3.7.1.4.dist-info/WHEEL
openseespy_mac_arm-3.7.1.4.dist-info/top_level.txt
openseespy_mac_arm-3.7.1.4.dist-info/METADATA
