Metadata-Version: 2.4
Name: openseespy-mac-arm
Version: 3.7.1.4
Summary: OpenSeesPy native for Apple Silicon (Mac M1/M2/M3/M4) - Lite version without MPI
Author-email: Orlando Arroyo <odarroyo@uc.cl>
License: GNU GPL v3
Requires-Python: >=3.12
Requires-Dist: numpy
